pynamodb_attributes/__init__.py
pynamodb_attributes/float.py
pynamodb_attributes/integer.py
pynamodb_attributes/integer_date.py
pynamodb_attributes/integer_enum.py
pynamodb_attributes/integer_set.py
pynamodb_attributes/py.typed
pynamodb_attributes/timedelta.py
pynamodb_attributes/timestamp.py
pynamodb_attributes/unicode_datetime.py
pynamodb_attributes/unicode_delimited_tuple.py
pynamodb_attributes/unicode_enum.py
pynamodb_attributes/unicode_protobuf_enum.py
pynamodb_attributes/uuid.py
tests/__init__.py
tests/conftest.py
tests/connection.py
tests/float_attribute_test.py
tests/integer_attribute_test.py
tests/integer_date_attribute_test.py
tests/integer_enum_attribute_test.py
tests/integer_set_attribute_test.py
tests/meta.py
tests/timedelta_attribute_test.py
tests/timestamp_attribute_test.py
tests/unicode_datetime_attribute_test.py
tests/unicode_delimited_tuple_attribute_test.py
tests/unicode_enum_attribute_test.py
tests/unicode_protobuf_enum_attribute_test.py
tests/uuid_attribute_test.py
pynamodb_attributes-0.5.0.dist-info/LICENSE
pynamodb_attributes-0.5.0.dist-info/METADATA
pynamodb_attributes-0.5.0.dist-info/WHEEL
pynamodb_attributes-0.5.0.dist-info/top_level.txt
pynamodb_attributes-0.5.0.dist-info/RECORD
