Metadata-Version: 2.1
Name: pynamodb-attributes
Version: 0.5.0
Summary: Common attributes for PynamoDB
Home-page: https://www.github.com/lyft/pynamodb-attributes
Maintainer: Lyft
Maintainer-email: ikonstantinov@lyft.com
Classifier: Programming Language :: Python :: 3
Classifier: Programming Language :: Python :: 3 :: Only
Requires-Python: >=3
License-File: LICENSE
Requires-Dist: pynamodb >=5.0.0
